openbb_seeking_alpha/__init__.py
openbb_seeking_alpha/models/__init__.py
openbb_seeking_alpha/models/calendar_earnings.py
openbb_seeking_alpha/models/forward_eps_estimates.py
openbb_seeking_alpha/models/forward_sales_estimates.py
openbb_seeking_alpha/py.typed
openbb_seeking_alpha/utils/__init__.py
openbb_seeking_alpha/utils/helpers.py
openbb_seeking_alpha-1.5.1.dist-info/METADATA
openbb_seeking_alpha-1.5.1.dist-info/WHEEL
openbb_seeking_alpha-1.5.1.dist-info/entry_points.txt
openbb_seeking_alpha-1.5.1.dist-info/RECORD
